{
    "gameobjects" :  [
        { "type": "tree", "x": 1313, "y": 334 },
        { "type": "tree", "x": 1330, "y": 1239 },
        { "type": "tree", "x": 1206, "y": 1243 },
        { "type": "tree", "x": 993, "y": 1446 },
        { "type": "tree", "x": 136, "y": 598 },
        { "type": "tree", "x": 853, "y": 1005 },
        { "type": "tree", "x": 1247, "y": 565 },
        { "type": "tree", "x": 995, "y": 56 },
        { "type": "tree", "x": 373, "y": 1248 },
        { "type": "tree", "x": 27, "y": 1858 },
        { "type": "tree", "x": 723, "y": 407 },
        { "type": "tree", "x": 897, "y": 416 },
        { "type": "tree", "x": 1149, "y": 931 },
        { "type": "tree", "x": 1921, "y": 780 },
        { "type": "tree", "x": 1791, "y": 704 },
        { "type": "tree", "x": 1381, "y": 512 },
        { "type": "crate", "x": 319, "y": 4 },
        { "type": "tree", "x": 768, "y": 153 },
        { "type": "tree", "x": 366, "y": 1394 },
        { "type": "tree", "x": 1902, "y": 1098 },
        { "type": "tree", "x": 291, "y": 1243 },
        { "type": "tree", "x": 1555, "y": 532 },
        { "type": "tree", "x": 745, "y": 855 },
        { "type": "tree", "x": 1299, "y": 714 },
        { "type": "tree", "x": 1013, "y": 1049 },
        { "type": "tree", "x": 356, "y": 1359 },
        { "type": "tree", "x": 1520, "y": 1366 },
        { "type": "tree", "x": 761, "y": 1101 },
        { "type": "tree", "x": 30, "y": 44 },
        { "type": "tree", "x": 424, "y": 1199 },
        { "type": "tree", "x": 1876, "y": 1404 },
        { "type": "tree", "x": 582, "y": 1074 },
        { "type": "tree", "x": 591, "y": 1480 },
        { "type": "tree", "x": 1308, "y": 1205 },
        { "type": "tree", "x": 1296, "y": 1739 },
        { "type": "tree", "x": 984, "y": 856 },
        { "type": "tree", "x": 821, "y": 1781 },
        { "type": "tree", "x": 1154, "y": 206 },
        { "type": "tree", "x": 174, "y": 713 },
        { "type": "tree", "x": 401, "y": 661 },
        { "type": "tree", "x": 849, "y": 1145 },
        { "type": "tree", "x": 1225, "y": 14 },
        { "type": "tree", "x": 838, "y": 402 },
        { "type": "tree", "x": 191, "y": 1154 },
        { "type": "tree", "x": 1697, "y": 1137 },
        { "type": "tree", "x": 641, "y": 694 },
        { "type": "tree", "x": 172, "y": 480 },
        { "type": "tree", "x": 1411, "y": 14 },
        { "type": "tree", "x": 699, "y": 1796 },
        { "type": "tree", "x": 327, "y": 730 },
        { "type": "tree", "x": 1107, "y": 1418 },
        { "type": "tree", "x": 1218, "y": 1160 },
        { "type": "tree", "x": 32, "y": 4 },
        { "type": "tree", "x": 388, "y": 1924 },
        { "type": "tree", "x": 1221, "y": 1061 },
        { "type": "tree", "x": 221, "y": 1491 },
        { "type": "tree", "x": 851, "y": 253 },
        { "type": "tree", "x": 494, "y": 1458 },
        { "type": "tree", "x": 1797, "y": 1550 },
        { "type": "tree", "x": 1118, "y": 824 },
        { "type": "tree", "x": 253, "y": 210 },
        { "type": "tree", "x": 1263, "y": 1 },
        { "type": "tree", "x": 850, "y": 1965 },
        { "type": "tree", "x": 1806, "y": 897 },
        { "type": "tree", "x": 1838, "y": 614 },
        { "type": "tree", "x": 967, "y": 1358 },
        { "type": "tree", "x": 1731, "y": 610 },
        { "type": "tree", "x": 1809, "y": 1647 },
        { "type": "tree", "x": 194, "y": 1863 },
        { "type": "tree", "x": 1794, "y": 165 },
        { "type": "tree", "x": 668, "y": 286 },
        { "type": "tree", "x": 1410, "y": 653 },
        { "type": "tree", "x": 1133, "y": 138 },
        { "type": "tree", "x": 466, "y": 450 },
        { "type": "tree", "x": 213, "y": 724 },
        { "type": "tree", "x": 1140, "y": 98 },
        { "type": "tree", "x": 1490, "y": 765 },
        { "type": "tree", "x": 1533, "y": 1850 },
        { "type": "tree", "x": 853, "y": 1054 },
        { "type": "tree", "x": 1379, "y": 676 },
        { "type": "tree", "x": 53, "y": 283 },
        { "type": "tree", "x": 432, "y": 1949 },
        { "type": "tree", "x": 900, "y": 1902 },
        { "type": "tree", "x": 796, "y": 903 },
        { "type": "tree", "x": 367, "y": 650 },
        { "type": "tree", "x": 398, "y": 835 },
        { "type": "tree", "x": 671, "y": 1550 },
        { "type": "tree", "x": 441, "y": 1623 },
        { "type": "tree", "x": 1396, "y": 689 },
        { "type": "tree", "x": 1200, "y": 782 },
        { "type": "tree", "x": 221, "y": 1572 },
        { "type": "tree", "x": 1366, "y": 319 },
        { "type": "tree", "x": 790, "y": 1185 },
        { "type": "tree", "x": 385, "y": 979 },
        { "type": "tree", "x": 1048, "y": 247 },
        { "type": "tree", "x": 209, "y": 992 },
        { "type": "tree", "x": 304, "y": 662 },
        { "type": "tree", "x": 1926, "y": 1229 },
        { "type": "tree", "x": 1821, "y": 1482 }
    ]
}